[
  {
    "inputs": [],
    "stateMutability": "nonpayable",
    "type": "constructor"
  },
  {
    "anonymous": false,
    "inputs": [
      {
        "indexed": true,
        "internalType": "bytes32",
        "name": "uridHash",
        "type": "bytes32"
      },
      {
        "indexed": false,
        "internalType": "uint256",
        "name": "familySize",
        "type": "uint256"
      },
      {
        "indexed": false,
        "internalType": "uint256",
        "name": "registrationTime",
        "type": "uint256"
      },
      {
        "indexed": false,
        "internalType": "address",
        "name": "registeredBy",
        "type": "address"
      }
    ],
    "name": "FamilyRegistered",
    "type": "event"
  },
  {
    "anonymous": false,
    "inputs": [
      {
        "indexed": true,
        "internalType": "bytes32",
        "name": "uridHash",
        "type": "bytes32"
      },
      {
        "indexed": false,
        "internalType": "bool",
        "name": "isActive",
        "type": "bool"
      },
      {
        "indexed": false,
        "internalType": "address",
        "name": "updatedBy",
        "type": "address"
      }
    ],
    "name": "FamilyStatusUpdated",
    "type": "event"
  },
  {
    "inputs": [
      {
        "internalType": "bytes32[]",
        "name": "_uridHashes",
        "type": "bytes32[]"
      },
      {
        "internalType": "uint256[]",
        "name": "_familySizes",
        "type": "uint256[]"
      }
    ],
    "name": "batchRegisterFamilies",
    "outputs": [],
    "stateMutability": "nonpayable",
    "type": "function"
  },
  {
    "inputs": [
      {
        "internalType": "bytes32",
        "name": "",
        "type": "bytes32"
      }
    ],
    "name": "families",
    "outputs": [
      {
        "internalType": "bytes32",
        "name": "uridHash",
        "type": "bytes32"
      },
      {
        "internalType": "uint256",
        "name": "familySize",
        "type": "uint256"
      },
      {
        "internalType": "uint256",
        "name": "registrationTime",
        "type": "uint256"
      },
      {
        "internalType": "address",
        "name": "registeredBy",
        "type": "address"
      },
      {
        "internalType": "bool",
        "name": "isActive",
        "type": "bool"
      },
      {
        "internalType": "bool",
        "name": "exists",
        "type": "bool"
      }
    ],
    "stateMutability": "view",
    "type": "function"
  },
  {
    "inputs": [
      {
        "internalType": "bytes32",
        "name": "_uridHash",
        "type": "bytes32"
      }
    ],
    "name": "getFamilyInfo",
    "outputs": [
      {
        "components": [
          {
            "internalType": "bytes32",
            "name": "uridHash",
            "type": "bytes32"
          },
          {
            "internalType": "uint256",
            "name": "familySize",
            "type": "uint256"
          },
          {
            "internalType": "uint256",
            "name": "registrationTime",
            "type": "uint256"
          },
          {
            "internalType": "address",
            "name": "registeredBy",
            "type": "address"
          },
          {
            "internalType": "bool",
            "name": "isActive",
            "type": "bool"
          },
          {
            "internalType": "bool",
            "name": "exists",
            "type": "bool"
          }
        ],
        "internalType": "struct URIDRegistry.Family",
        "name": "",
        "type": "tuple"
      }
    ],
    "stateMutability": "view",
    "type": "function"
  },
  {
    "inputs": [],
    "name": "getContractStats",
    "outputs": [
      {
        "internalType": "uint256",
        "name": "totalFamilies_",
        "type": "uint256"
      },
      {
        "internalType": "uint256",
        "name": "activeFamilies",
        "type": "uint256"
      },
      {
        "internalType": "uint256",
        "name": "contractBalance",
        "type": "uint256"
      }
    ],
    "stateMutability": "view",
    "type": "function"
  },
  {
    "inputs": [
      {
        "internalType": "address",
        "name": "_registrar",
        "type": "address"
      }
    ],
    "name": "getRegistrationCount",
    "outputs": [
      {
        "internalType": "uint256",
        "name": "",
        "type": "uint256"
      }
    ],
    "stateMutability": "view",
    "type": "function"
  },
  {
    "inputs": [],
    "name": "getTotalFamilies",
    "outputs": [
      {
        "internalType": "uint256",
        "name": "",
        "type": "uint256"
      }
    ],
    "stateMutability": "view",
    "type": "function"
  },
  {
    "inputs": [
      {
        "internalType": "bytes32",
        "name": "_uridHash",
        "type": "bytes32"
      }
    ],
    "name": "isURIDRegistered",
    "outputs": [
      {
        "internalType": "bool",
        "name": "",
        "type": "bool"
      }
    ],
    "stateMutability": "view",
    "type": "function"
  },
  {
    "inputs": [
      {
        "internalType": "bytes32",
        "name": "_uridHash",
        "type": "bytes32"
      }
    ],
    "name": "isValidFamily",
    "outputs": [
      {
        "internalType": "bool",
        "name": "",
        "type": "bool"
      }
    ],
    "stateMutability": "view",
    "type": "function"
  },
  {
    "inputs": [],
    "name": "owner",
    "outputs": [
      {
        "internalType": "address",
        "name": "",
        "type": "address"
      }
    ],
    "stateMutability": "view",
    "type": "function"
  },
  {
    "inputs": [
      {
        "internalType": "bytes32",
        "name": "_uridHash",
        "type": "bytes32"
      },
      {
        "internalType": "uint256",
        "name": "_familySize",
        "type": "uint256"
      }
    ],
    "name": "registerFamily",
    "outputs": [],
    "stateMutability": "nonpayable",
    "type": "function"
  },
  {
    "inputs": [
      {
        "internalType": "address",
        "name": "",
        "type": "address"
      }
    ],
    "name": "registrationCount",
    "outputs": [
      {
        "internalType": "uint256",
        "name": "",
        "type": "uint256"
      }
    ],
    "stateMutability": "view",
    "type": "function"
  },
  {
    "inputs": [
      {
        "internalType": "bytes32",
        "name": "",
        "type": "bytes32"
      }
    ],
    "name": "registeredURIDs",
    "outputs": [
      {
        "internalType": "bool",
        "name": "",
        "type": "bool"
      }
    ],
    "stateMutability": "view",
    "type": "function"
  },
  {
    "inputs": [],
    "name": "totalFamilies",
    "outputs": [
      {
        "internalType": "uint256",
        "name": "",
        "type": "uint256"
      }
    ],
    "stateMutability": "view",
    "type": "function"
  },
  {
    "inputs": [
      {
        "internalType": "address",
        "name": "_newOwner",
        "type": "address"
      }
    ],
    "name": "transferOwnership",
    "outputs": [],
    "stateMutability": "nonpayable",
    "type": "function"
  },
  {
    "inputs": [
      {
        "internalType": "bytes32",
        "name": "_uridHash",
        "type": "bytes32"
      },
      {
        "internalType": "bool",
        "name": "_isActive",
        "type": "bool"
      }
    ],
    "name": "updateFamilyStatus",
    "outputs": [],
    "stateMutability": "nonpayable",
    "type": "function"
  }
]